universe_matrix/__init__.py
universe_matrix-0.0.3.dist-info/LICENSE
universe_matrix-0.0.3.dist-info/METADATA
universe_matrix-0.0.3.dist-info/WHEEL
universe_matrix-0.0.3.dist-info/top_level.txt
universe_matrix-0.0.3.dist-info/RECORD
