Metadata-Version: 2.1
Name: universe-matrix
Version: 0.0.3
Summary: Wrapper for Multivalue Data
Home-page: https://github.com/Krowemoh/universe_matrix
Author: Nivethan Thiyagarajah
Author-email: nivethant@asynchronsystems.com
License: UNKNOWN
Platform: UNKNOWN
